webgpu/__init__.py
webgpu/_version.py
webgpu/camera.py
webgpu/canvas.py
webgpu/clipping.py
webgpu/colormap.py
webgpu/draw.py
webgpu/font.bin
webgpu/font.py
webgpu/input_handler.py
webgpu/jupyter.py
webgpu/jupyter_pyodide.py
webgpu/labels.py
webgpu/light.py
webgpu/lilgui.py
webgpu/platform.py
webgpu/renderer.py
webgpu/scene.py
webgpu/shapes.py
webgpu/triangles.py
webgpu/uniforms.py
webgpu/utils.py
webgpu/vectors.py
webgpu/webgpu_api.py
webgpu/link/__init__.py
webgpu/link/base.py
webgpu/link/link.js
webgpu/link/proxy.py
webgpu/link/websocket.py
webgpu/shaders/camera.wgsl
webgpu/shaders/clipping.wgsl
webgpu/shaders/colormap.wgsl
webgpu/shaders/font.wgsl
webgpu/shaders/light.wgsl
webgpu/shaders/shapes.wgsl
webgpu/shaders/text.wgsl
webgpu/shaders/triangulation.wgsl
webgpu/shaders/vector.wgsl
webgpu-1.1.0.dist-info/licenses/LICENSE
webgpu-1.1.0.dist-info/METADATA
webgpu-1.1.0.dist-info/WHEEL
webgpu-1.1.0.dist-info/top_level.txt
webgpu-1.1.0.dist-info/RECORD
