Metadata-Version: 2.4
Name: webgpu
Version: 1.1.0
Summary: A Python based WebGPU API using pyodide
Author-email: Matthias Hochsteger <mhochsteger@cerbsim.com>, Christopher Lackner <clackner@cerbsim.com>
License-Expression: LGPL-2.1-or-later
Keywords: webgpu,compute shaders,graphics,python,pyodide,wgsl
Classifier: Programming Language :: Python :: 3
Classifier: Operating System :: OS Independent
Requires-Python: >=3.8
License-File: LICENSE
Requires-Dist: numpy
Requires-Dist: requests
Requires-Dist: packaging
Provides-Extra: test
Requires-Dist: pytest; extra == "test"
Requires-Dist: pytest-pyodide; extra == "test"
Dynamic: license-file
